{
  "episode_rewards": [
    1.1,
    1.3,
    1.167,
    1.667,
    1.8,
    0.833,
    1.6,
    1.5,
    1.8,
    1.8,
    0.8,
    1.2,
    1.0,
    1.8,
    1.1,
    1.6,
    1.6,
    0.8,
    1.0,
    1.1,
    1.0,
    1.067,
    1.3,
    0.9,
    1.6,
    1.5,
    1.2,
    1.267,
    1.2,
    1.3,
    1.6,
    1.167,
    1.167,
    1.533,
    1.0,
    1.1,
    1.2,
    0.8,
    1.1,
    0.9,
    1.3,
    1.1,
    0.967,
    1.033,
    1.2,
    1.6,
    1.1,
    0.4,
    1.6,
    0.8,
    1.1,
    0.7,
    1.1,
    1.2,
    1.8,
    1.167,
    1.7,
    1.8,
    1.8,
    1.467,
    1.2,
    1.2,
    1.4,
    1.0,
    1.1,
    1.1,
    1.3,
    1.1,
    1.1,
    1.167,
    1.5,
    1.8,
    1.1,
    1.5,
    1.7,
    1.167,
    1.0,
    1.3,
    0.8,
    1.1,
    0.633,
    1.4,
    1.6,
    1.4,
    2.0,
    1.2,
    1.8,
    1.0,
    1.167,
    1.3,
    1.2,
    1.3,
    1.0,
    1.4,
    1.0,
    1.8,
    1.6,
    1.7,
    1.2,
    0.7,
    -8.782,
    -19.796,
    -32.889,
    -28.453,
    -21.528,
    -15.758,
    -28.23,
    -21.955,
    -25.139,
    -28.22,
    -22.43,
    -20.439,
    -24.694,
    -21.361,
    -20.612,
    -39.982,
    -2.376,
    -18.398,
    -26.532,
    -26.303,
    -13.983,
    -24.204,
    -23.959,
    -36.013,
    -22.05,
    -21.537,
    -28.307,
    -27.26,
    -25.771,
    -22.752,
    -28.255,
    -23.822,
    -16.955,
    -26.24,
    -22.894,
    -27.724,
    -31.207,
    -23.391,
    -25.404,
    -17.978,
    -16.371,
    -23.771,
    -25.22,
    -41.006,
    -16.39,
    -21.49,
    0.423,
    -17.842,
    -25.529,
    -26.248,
    -29.905,
    -32.356,
    -33.182,
    -31.415,
    -20.559,
    16.183,
    -28.616,
    -25.738,
    -22.696,
    -30.642,
    -19.834,
    -26.962,
    -40.817,
    -32.054,
    -29.852,
    -32.588,
    -24.685,
    -22.803,
    -14.483,
    -38.362,
    -29.135,
    -39.399,
    -12.318,
    -25.426,
    13.876,
    -10.563,
    -19.14,
    -23.477,
    -34.003,
    -21.563,
    -18.144,
    -16.49,
    -10.271,
    -34.062,
    -19.856,
    -22.391,
    -28.556,
    -18.963,
    -20.668,
    -22.449,
    55.172,
    -10.135,
    -26.066,
    -37.891,
    -14.918,
    -36.072,
    -29.934,
    -24.485,
    -28.264,
    -14.624,
    -167.134,
    -153.975,
    -161.828,
    -146.544,
    -161.655,
    -161.19,
    -154.799,
    -138.168,
    -138.938,
    -150.968,
    -166.547,
    -154.84,
    -164.467,
    -146.762,
    -146.292,
    -165.88,
    -157.041,
    -160.927,
    -159.558,
    -155.372,
    -151.076,
    -155.773,
    -156.68,
    -146.439,
    -158.604,
    -132.933,
    -172.964,
    -170.869,
    -145.046,
    -168.541,
    -149.549,
    -140.195,
    -172.057,
    -145.531,
    -168.834,
    -147.518,
    -162.43,
    -156.164,
    -146.361,
    -163.026,
    -159.072,
    -161.301,
    -151.612,
    -138.954,
    -146.144,
    -154.064,
    -144.925,
    -159.948,
    -153.558,
    -172.279,
    1.6,
    1.1,
    1.3,
    2.0,
    2.0,
    1.8,
    1.1,
    1.6,
    1.3,
    1.4,
    1.9,
    1.6,
    1.0,
    1.1,
    1.5,
    1.3,
    1.6,
    1.5,
    1.1,
    1.4,
    2.2,
    1.5,
    1.2,
    1.0,
    1.0,
    1.5,
    1.3,
    1.3,
    1.2,
    1.1,
    0.9,
    1.8,
    1.3,
    1.8,
    1.4,
    1.1,
    1.6,
    1.0,
    1.1,
    1.6,
    0.9,
    1.1,
    1.6,
    0.9,
    1.8,
    1.6,
    1.2,
    1.3,
    2.2,
    0.7
  ],
  "baseline_metrics": {
    "patients_saved": 4.0,
    "patients_lost": 0.0,
    "waste_pct": 0.0,
    "cooperation_pct": 100,
    "avg_reward": 1.2,
    "resources_used": 6.3
  },
  "trained_metrics": {
    "patients_saved": 4.0,
    "patients_lost": 0.0,
    "waste_pct": 0.0,
    "cooperation_pct": 100,
    "avg_reward": 1.4,
    "resources_used": 6.1
  },
  "num_episodes": 300
}